pasteboard2/__init__.py
pasteboard2/__main__.py
pasteboard2/pasteboard2.py
pasteboard2-0.0.6.dist-info/METADATA
pasteboard2-0.0.6.dist-info/WHEEL
pasteboard2-0.0.6.dist-info/entry_points.txt
pasteboard2-0.0.6.dist-info/licenses/LICENSE.txt
pasteboard2-0.0.6.dist-info/RECORD
