Metadata-Version: 2.1
Name: pasteboard2
Version: 0.0.6
Summary: access macOS pasteboard
Project-URL: Homepage, https://github.com/bwagner/pasteboard2
Project-URL: Bug Tracker, https://github.com/bwagner/pasteboard2/issues
Author-email: Bernhard Wagner <pasteboard2@nosuch.biz>
License: Copyright (c) 2018 The Python Packaging Authority
License-File: LICENSE.txt
Classifier: License :: OSI Approved :: MIT License
Classifier: Operating System :: MacOS :: MacOS X
Classifier: Programming Language :: Python :: 3
Requires-Python: >=3.7
Requires-Dist: pyobjc
Requires-Dist: pytest
Requires-Dist: typer
